<?xml version="1.0" encoding="utf-8"?>
<!--Catalan-->
<CultureInfo name="ca">
  <Calendar>System.Globalization.GregorianCalendar</Calendar>
  <CompareInfo LCID="3" />
  <DisplayNames>
    <DisplayName lang="ar">ca (Needs translation)</DisplayName>
    <DisplayName lang="bg">ca (Needs translation)</DisplayName>
    <DisplayName lang="ca">ca (Needs translation)</DisplayName>
    <DisplayName lang="zh-CHS">ca (Needs translation)</DisplayName>
    <DisplayName lang="zh-CHT">ca (Needs translation)</DisplayName>
    <DisplayName lang="cs">ca (Needs translation)</DisplayName>
    <DisplayName lang="da">ca (Needs translation)</DisplayName>
    <DisplayName lang="de">ca (Needs translation)</DisplayName>
    <DisplayName lang="el">ca (Needs translation)</DisplayName>
    <DisplayName lang="en">ca (Needs translation)</DisplayName>
    <DisplayName lang="es">ca (Needs translation)</DisplayName>
    <DisplayName lang="fi">ca (Needs translation)</DisplayName>
    <DisplayName lang="fr">ca (Needs translation)</DisplayName>
    <DisplayName lang="he">ca (Needs translation)</DisplayName>
    <DisplayName lang="hu">ca (Needs translation)</DisplayName>
    <DisplayName lang="is">ca (Needs translation)</DisplayName>
    <DisplayName lang="it">ca (Needs translation)</DisplayName>
    <DisplayName lang="ja">ca (Needs translation)</DisplayName>
    <DisplayName lang="ko">ca (Needs translation)</DisplayName>
    <DisplayName lang="nl">ca (Needs translation)</DisplayName>
    <DisplayName lang="no">ca (Needs translation)</DisplayName>
    <DisplayName lang="pl">ca (Needs translation)</DisplayName>
    <DisplayName lang="pt">ca (Needs translation)</DisplayName>
    <DisplayName lang="ro">ca (Needs translation)</DisplayName>
    <DisplayName lang="ru">ca (Needs translation)</DisplayName>
    <DisplayName lang="hr">ca (Needs translation)</DisplayName>
    <DisplayName lang="sk">ca (Needs translation)</DisplayName>
    <DisplayName lang="sq">ca (Needs translation)</DisplayName>
    <DisplayName lang="sv">ca (Needs translation)</DisplayName>
    <DisplayName lang="th">ca (Needs translation)</DisplayName>
    <DisplayName lang="tr">ca (Needs translation)</DisplayName>
    <DisplayName lang="ur">ca (Needs translation)</DisplayName>
    <DisplayName lang="id">ca (Needs translation)</DisplayName>
    <DisplayName lang="uk">ca (Needs translation)</DisplayName>
    <DisplayName lang="be">ca (Needs translation)</DisplayName>
    <DisplayName lang="sl">ca (Needs translation)</DisplayName>
    <DisplayName lang="et">ca (Needs translation)</DisplayName>
    <DisplayName lang="lv">ca (Needs translation)</DisplayName>
    <DisplayName lang="lt">ca (Needs translation)</DisplayName>
    <DisplayName lang="fa">ca (Needs translation)</DisplayName>
    <DisplayName lang="vi">ca (Needs translation)</DisplayName>
    <DisplayName lang="hy">ca (Needs translation)</DisplayName>
    <DisplayName lang="az">ca (Needs translation)</DisplayName>
    <DisplayName lang="eu">ca (Needs translation)</DisplayName>
    <DisplayName lang="mk">ca (Needs translation)</DisplayName>
    <DisplayName lang="af">ca (Needs translation)</DisplayName>
    <DisplayName lang="ka">ca (Needs translation)</DisplayName>
    <DisplayName lang="fo">ca (Needs translation)</DisplayName>
    <DisplayName lang="hi">ca (Needs translation)</DisplayName>
    <DisplayName lang="ms">ca (Needs translation)</DisplayName>
    <DisplayName lang="kk">ca (Needs translation)</DisplayName>
    <DisplayName lang="ky">ca (Needs translation)</DisplayName>
    <DisplayName lang="sw">ca (Needs translation)</DisplayName>
    <DisplayName lang="uz">ca (Needs translation)</DisplayName>
    <DisplayName lang="tt">ca (Needs translation)</DisplayName>
    <DisplayName lang="pa">ca (Needs translation)</DisplayName>
    <DisplayName lang="gu">ca (Needs translation)</DisplayName>
    <DisplayName lang="ta">ca (Needs translation)</DisplayName>
    <DisplayName lang="te">ca (Needs translation)</DisplayName>
    <DisplayName lang="kn">ca (Needs translation)</DisplayName>
    <DisplayName lang="mr">ca (Needs translation)</DisplayName>
    <DisplayName lang="sa">ca (Needs translation)</DisplayName>
    <DisplayName lang="mn">ca (Needs translation)</DisplayName>
    <DisplayName lang="gl">ca (Needs translation)</DisplayName>
    <DisplayName lang="kok">ca (Needs translation)</DisplayName>
    <DisplayName lang="syr">ca (Needs translation)</DisplayName>
    <DisplayName lang="div">ca (Needs translation)</DisplayName>
  </DisplayNames>
  <EnglishName>ca (Need English name)</EnglishName>
  <LCID>3</LCID>
  <Name>ca</Name>
  <NativeName>ca (Need native name)</NativeName>
  <OptionalCalendars>
    <Calendar>System.Globalization.GregorianCalendar</Calendar>
  </OptionalCalendars>
  <TextInfo>
    <ANSICodePage>1252</ANSICodePage>
    <EBCDICCodePage>500</EBCDICCodePage>
    <ListSeparator>;</ListSeparator>
    <MacCodePage>10000</MacCodePage>
    <OEMCodePage>850</OEMCodePage>
  </TextInfo>
  <ThreeLetterWindowsLanguageName>CAT</ThreeLetterWindowsLanguageName>
  <ThreeLetterISOLanguageName>cat</ThreeLetterISOLanguageName>
  <TwoLetterISOLanguageName>ca</TwoLetterISOLanguageName>
</CultureInfo>